[
  {
    "src": "https://randomuser.me/api/portraits/med/women/56.jpg"
  },
  {
    "src": "https://randomuser.me/api/portraits/med/men/5.jpg"
  },
  {
    "src": "https://randomuser.me/api/portraits/med/men/91.jpg"
  },
  {
    "src": "https://randomuser.me/api/portraits/med/men/10.jpg"
  },
  {
    "src": "https://randomuser.me/api/portraits/med/women/90.jpg"
  },
  {
    "src": "https://randomuser.me/api/portraits/med/men/56.jpg"
  },
  {
    "src": "https://randomuser.me/api/portraits/med/women/92.jpg"
  },
  {
    "src": "https://randomuser.me/api/portraits/med/women/22.jpg"
  },
  {
    "src": "https://randomuser.me/api/portraits/med/women/94.jpg"
  },
  {
    "src": "https://randomuser.me/api/portraits/med/women/2.jpg"
  },
  {
    "src": "https://randomuser.me/api/portraits/med/men/23.jpg"
  }
]
